texforge/__init__.py
texforge/aps_reviewer.py
texforge/arxiv_downloader.py
texforge/auto_maintain_paper.py
texforge/autonomous_writer.py
texforge/bibliography_manager.py
texforge/brainstorming.py
texforge/cli.py
texforge/config.py
texforge/cover_letter_writer.py
texforge/daily_digest.py
texforge/exceptions.py
texforge/master_orchestrator.py
texforge/notification_cli.py
texforge/notifications.py
texforge/pdf_compiler.py
texforge/peer_review.py
texforge/polish_agent.py
texforge/progressive_writer.py
texforge/prover_agent.py
texforge/validate_paper.py
texforge-0.1.4.dist-info/licenses/LICENSE
texforge-0.1.4.dist-info/METADATA
texforge-0.1.4.dist-info/WHEEL
texforge-0.1.4.dist-info/entry_points.txt
texforge-0.1.4.dist-info/top_level.txt
texforge-0.1.4.dist-info/RECORD
