Metadata-Version: 2.4
Name: texforge
Version: 0.1.4
Summary: TexForge - Forge perfect LaTeX papers with automated compilation, validation, and maintenance
Author-email: Jue Xu <xujue@connect.hku.hk>
License: GPL-3.0-or-later
Project-URL: Homepage, https://github.com/Jue-Xu/LaTex-paper-automation
Project-URL: Repository, https://github.com/Jue-Xu/LaTex-paper-automation
Project-URL: Issues, https://github.com/Jue-Xu/LaTex-paper-automation/issues
Keywords: latex,paper,research,automation,compilation,validation,academic
Classifier: Development Status :: 3 - Alpha
Classifier: Intended Audience :: Science/Research
Classifier: License :: OSI Approved :: GNU General Public License v3 or later (GPLv3+)
Classifier: Operating System :: OS Independent
Classifier: Programming Language :: Python :: 3
Classifier: Programming Language :: Python :: 3.8
Classifier: Programming Language :: Python :: 3.9
Classifier: Programming Language :: Python :: 3.10
Classifier: Programming Language :: Python :: 3.11
Classifier: Programming Language :: Python :: 3.12
Classifier: Topic :: Text Processing :: Markup :: LaTeX
Classifier: Topic :: Scientific/Engineering
Classifier: Topic :: Software Development :: Build Tools
Classifier: Environment :: Console
Requires-Python: >=3.8
License-File: LICENSE
Requires-Dist: requests>=2.28.0
Requires-Dist: numpy>=1.21.0
Requires-Dist: matplotlib>=3.5.0
Requires-Dist: pyyaml>=6.0
Provides-Extra: dev
Requires-Dist: pytest>=7.0.0; extra == "dev"
Requires-Dist: black>=22.0.0; extra == "dev"
Requires-Dist: flake8>=4.0.0; extra == "dev"
Dynamic: license-file
